dibujos/__init__.py
dibujos/funciones_dibujos.py
matematicas/__init__.py
matematicas/funciones_matematicas.py
GTDMfunctions-0.0.2.dist-info/METADATA
GTDMfunctions-0.0.2.dist-info/WHEEL
GTDMfunctions-0.0.2.dist-info/top_level.txt
GTDMfunctions-0.0.2.dist-info/RECORD
