Metadata-Version: 2.1
Name: GTDMfunctions
Version: 0.0.2
Requires-Dist: numpy
Requires-Dist: scipy
Requires-Dist: sympy
Requires-Dist: matplotlib
